src/__init__.py
src/preamble.py
src/tactile.py
src/tiling_data.py
tactile/__init__.py
tactile/preamble.py
tactile/tactile.py
tactile/tiling_data.py
tactile-0.1.0.dist-info/LICENSE
tactile-0.1.0.dist-info/METADATA
tactile-0.1.0.dist-info/WHEEL
tactile-0.1.0.dist-info/top_level.txt
tactile-0.1.0.dist-info/RECORD
