Metadata-Version: 2.1
Name: tactile
Version: 0.1.0
Summary: Python module for representing, manipulating, and drawing tilings of the 2D plane.
Home-page: https://github.com/DBraun/tactile-python
Author: David Braun
Author-email: braun@ccrma.stanford.edu
Project-URL: Bug Tracker, https://github.com/DBraun/tactile-python/issues
Keywords: tiling,tessellation,tessellations,geometry
Classifier: Programming Language :: Python :: 3
Classifier: License :: OSI Approved :: BSD License
Classifier: Operating System :: OS Independent
Requires-Python: >=3.6
License-File: LICENSE
